textual_enhanced/__init__.py
textual_enhanced/__main__.py
textual_enhanced/app.py
textual_enhanced/binding.py
textual_enhanced/commands/__init__.py
textual_enhanced/commands/bindings.py
textual_enhanced/commands/command.py
textual_enhanced/commands/common.py
textual_enhanced/commands/provider.py
textual_enhanced/containers.py
textual_enhanced/dialogs/__init__.py
textual_enhanced/dialogs/confirm.py
textual_enhanced/dialogs/help.py
textual_enhanced/dialogs/modal_input.py
textual_enhanced/py.typed
textual_enhanced/screen.py
textual_enhanced/tools/__init__.py
textual_enhanced/tools/add_key_name.py
textual_enhanced/tools/history.py
textual_enhanced/widgets/__init__.py
textual_enhanced/widgets/option_list.py
textual_enhanced/widgets/text_viewer.py
textual_enhanced-1.2.0.dist-info/WHEEL
textual_enhanced-1.2.0.dist-info/METADATA
textual_enhanced-1.2.0.dist-info/RECORD
