Metadata-Version: 2.4
Name: textual-enhanced
Version: 1.2.0
Summary: A library of mildly-opinionated enhancements to Textual
Keywords: terminal,library,tui,framework
Author: Dave Pearson
Author-email: Dave Pearson <davep@davep.org>
License-Expression: MIT
Classifier: Development Status :: 5 - Production/Stable
Classifier: Environment :: Console
Classifier: Intended Audience :: Developers
Classifier: Operating System :: OS Independent
Classifier: Programming Language :: Python :: 3.10
Classifier: Programming Language :: Python :: 3.11
Classifier: Programming Language :: Python :: 3.12
Classifier: Programming Language :: Python :: 3.13
Classifier: Programming Language :: Python :: 3.14
Classifier: Topic :: Terminals
Classifier: Topic :: Software Development :: Libraries
Classifier: Typing :: Typed
Requires-Dist: textual>=1.0.0
Requires-Python: >=3.10
Project-URL: Discussions, https://github.com/davep/textual-enhanced/discussions
Project-URL: Documentation, https://textual-enhanced.davep.dev/
Project-URL: Homepage, https://textual-enhanced.davep.dev/
Project-URL: Issues, https://github.com/davep/textual-enhanced/issues
Project-URL: Repository, https://github.com/davep/textual-enhanced
Project-URL: Source, https://github.com/davep/textual-enhanced
